Workbook

Sheet Reco
A1: PAVAN JAIN S AND CO |CHARTERED ACCOUNTANTS
A3: AIS/TIS/26AS/BOOKS COMPARATIVE TOOL
A5: NAME OF THE CLIENT
A6: ASSESSMENT YEAR
A7: FINANCIAL YEAR
A8: PREPARED BY
C9: =SUBTOTAL(9,C12:C161) | D9: =SUBTOTAL(9,D12:D161) | E9: =SUBTOTAL(9,E12:E161) | F9: =SUBTOTAL(9,F12:F161) | G9: =SUBTOTAL(9,G12:G161) | H9: =SUBTOTAL(9,H12:H161) | I9: =SUBTOTAL(9,I12:I161) | J9: =SUBTOTAL(9,J12:J161) | ... P9: =SUBTOTAL(9,P12:P161) | Q9: =SUBTOTAL(9,Q12:Q65) | R9: =SUBTOTAL(9,R12:R65)
A10: Nature of Transactions | B10: Name of Party | C10: 26AS | E10: AIS | G10: TIS | I10: Books | K10: Difference | S10: Does the difference tantamounts to short declaration in Books? | T10: Action | U10: Remarks | V10: Summary Include
C11: Gross Value | D11: TDS/TCS | E11: Gross Value | F11: TDS/TCS | G11: Gross Value | H11: TDS/TCS | I11: Gross Value | J11: TDS/TCS | K11: 26AS/AIS | M11: 26AS/TIS | O11: AIS/TIS | Q11: Books/AIS
K12: =IF(OR(C12="",E12="",C12="NA",E12="NA"),"",ROUND(C12-E12,-1)) | L12: =IF(OR(D12="",F12="",D12="NA",F12="NA"),"",ROUND(D12-F12,-1)) | M12: =IF(OR(C12="",G12="",C12="NA",G12="NA"),"",ROUND(C12-G12,-1)) | N12: =IF(OR(D12="",H12="",D12="NA",H12="NA"),"",ROUND(D12-H12,-1)) | O12: =IF(OR(E12="",G12="",E12="NA",G12="NA"),"",ROUND(E12-G12,-1)) | P12: =IF(OR(F12="",H12="",F12="NA",H12="NA"),"",ROUND(F12-H12,-1)) | Q12: =IF(OR(E12="",I12="",E12="NA",I12="NA"),"",ROUND(IF(E12>I12,E12-I12,0),-1)) | R12: =IF(OR(F12="",J12="",F12="NA",J12="NA"),"",ROUND(IF(F12>J12,F12-J12,0),-1)) | T12: =IF(S12="Yes","Report","No Action") | V12: Y
K13: =IF(OR(C13="",E13="",C13="NA",E13="NA"),"",ROUND(C13-E13,-1)) | L13: =IF(OR(D13="",F13="",D13="NA",F13="NA"),"",ROUND(D13-F13,-1)) | M13: =IF(OR(C13="",G13="",C13="NA",G13="NA"),"",ROUND(C13-G13,-1)) | N13: =IF(OR(D13="",H13="",D13="NA",H13="NA"),"",ROUND(D13-H13,-1)) | O13: =IF(OR(E13="",G13="",E13="NA",G13="NA"),"",ROUND(E13-G13,-1)) | P13: =IF(OR(F13="",H13="",F13="NA",H13="NA"),"",ROUND(F13-H13,-1)) | Q13: =IF(OR(E13="",I13="",E13="NA",I13="NA"),"",ROUND(IF(E13>I13,E13-I13,0),-1)) | R13: =IF(OR(F13="",J13="",F13="NA",J13="NA"),"",ROUND(IF(F13>J13,F13-J13,0),-1)) | T13: =IF(S13="Yes","Report","No Action") | V13: Y
K14: =IF(OR(C14="",E14="",C14="NA",E14="NA"),"",ROUND(C14-E14,-1)) | L14: =IF(OR(D14="",F14="",D14="NA",F14="NA"),"",ROUND(D14-F14,-1)) | M14: =IF(OR(C14="",G14="",C14="NA",G14="NA"),"",ROUND(C14-G14,-1)) | N14: =IF(OR(D14="",H14="",D14="NA",H14="NA"),"",ROUND(D14-H14,-1)) | O14: =IF(OR(E14="",G14="",E14="NA",G14="NA"),"",ROUND(E14-G14,-1)) | P14: =IF(OR(F14="",H14="",F14="NA",H14="NA"),"",ROUND(F14-H14,-1)) | Q14: =IF(OR(E14="",I14="",E14="NA",I14="NA"),"",ROUND(IF(E14>I14,E14-I14,0),-1)) | R14: =IF(OR(F14="",J14="",F14="NA",J14="NA"),"",ROUND(IF(F14>J14,F14-J14,0),-1)) | T14: =IF(S14="Yes","Report","No Action") | V14: Y
K15: =IF(OR(C15="",E15="",C15="NA",E15="NA"),"",ROUND(C15-E15,-1)) | L15: =IF(OR(D15="",F15="",D15="NA",F15="NA"),"",ROUND(D15-F15,-1)) | M15: =IF(OR(C15="",G15="",C15="NA",G15="NA"),"",ROUND(C15-G15,-1)) | N15: =IF(OR(D15="",H15="",D15="NA",H15="NA"),"",ROUND(D15-H15,-1)) | O15: =IF(OR(E15="",G15="",E15="NA",G15="NA"),"",ROUND(E15-G15,-1)) | P15: =IF(OR(F15="",H15="",F15="NA",H15="NA"),"",ROUND(F15-H15,-1)) | Q15: =IF(OR(E15="",I15="",E15="NA",I15="NA"),"",ROUND(IF(E15>I15,E15-I15,0),-1)) | R15: =IF(OR(F15="",J15="",F15="NA",J15="NA"),"",ROUND(IF(F15>J15,F15-J15,0),-1)) | T15: =IF(S15="Yes","Report","No Action") | V15: Y
K16: =IF(OR(C16="",E16="",C16="NA",E16="NA"),"",ROUND(C16-E16,-1)) | L16: =IF(OR(D16="",F16="",D16="NA",F16="NA"),"",ROUND(D16-F16,-1)) | M16: =IF(OR(C16="",G16="",C16="NA",G16="NA"),"",ROUND(C16-G16,-1)) | N16: =IF(OR(D16="",H16="",D16="NA",H16="NA"),"",ROUND(D16-H16,-1)) | O16: =IF(OR(E16="",G16="",E16="NA",G16="NA"),"",ROUND(E16-G16,-1)) | P16: =IF(OR(F16="",H16="",F16="NA",H16="NA"),"",ROUND(F16-H16,-1)) | Q16: =IF(OR(E16="",I16="",E16="NA",I16="NA"),"",ROUND(IF(E16>I16,E16-I16,0),-1)) | R16: =IF(OR(F16="",J16="",F16="NA",J16="NA"),"",ROUND(IF(F16>J16,F16-J16,0),-1)) | T16: =IF(S16="Yes","Report","No Action") | V16: Y
K17: =IF(OR(C17="",E17="",C17="NA",E17="NA"),"",ROUND(C17-E17,-1)) | L17: =IF(OR(D17="",F17="",D17="NA",F17="NA"),"",ROUND(D17-F17,-1)) | M17: =IF(OR(C17="",G17="",C17="NA",G17="NA"),"",ROUND(C17-G17,-1)) | N17: =IF(OR(D17="",H17="",D17="NA",H17="NA"),"",ROUND(D17-H17,-1)) | O17: =IF(OR(E17="",G17="",E17="NA",G17="NA"),"",ROUND(E17-G17,-1)) | P17: =IF(OR(F17="",H17="",F17="NA",H17="NA"),"",ROUND(F17-H17,-1)) | Q17: =IF(OR(E17="",I17="",E17="NA",I17="NA"),"",ROUND(IF(E17>I17,E17-I17,0),-1)) | R17: =IF(OR(F17="",J17="",F17="NA",J17="NA"),"",ROUND(IF(F17>J17,F17-J17,0),-1)) | T17: =IF(S17="Yes","Report","No Action") | V17: Y
K18: =IF(OR(C18="",E18="",C18="NA",E18="NA"),"",ROUND(C18-E18,-1)) | L18: =IF(OR(D18="",F18="",D18="NA",F18="NA"),"",ROUND(D18-F18,-1)) | M18: =IF(OR(C18="",G18="",C18="NA",G18="NA"),"",ROUND(C18-G18,-1)) | N18: =IF(OR(D18="",H18="",D18="NA",H18="NA"),"",ROUND(D18-H18,-1)) | O18: =IF(OR(E18="",G18="",E18="NA",G18="NA"),"",ROUND(E18-G18,-1)) | P18: =IF(OR(F18="",H18="",F18="NA",H18="NA"),"",ROUND(F18-H18,-1)) | Q18: =IF(OR(E18="",I18="",E18="NA",I18="NA"),"",ROUND(IF(E18>I18,E18-I18,0),-1)) | R18: =IF(OR(F18="",J18="",F18="NA",J18="NA"),"",ROUND(IF(F18>J18,F18-J18,0),-1)) | T18: =IF(S18="Yes","Report","No Action") | V18: Y
K19: =IF(OR(C19="",E19="",C19="NA",E19="NA"),"",ROUND(C19-E19,-1)) | L19: =IF(OR(D19="",F19="",D19="NA",F19="NA"),"",ROUND(D19-F19,-1)) | M19: =IF(OR(C19="",G19="",C19="NA",G19="NA"),"",ROUND(C19-G19,-1)) | N19: =IF(OR(D19="",H19="",D19="NA",H19="NA"),"",ROUND(D19-H19,-1)) | O19: =IF(OR(E19="",G19="",E19="NA",G19="NA"),"",ROUND(E19-G19,-1)) | P19: =IF(OR(F19="",H19="",F19="NA",H19="NA"),"",ROUND(F19-H19,-1)) | Q19: =IF(OR(E19="",I19="",E19="NA",I19="NA"),"",ROUND(IF(E19>I19,E19-I19,0),-1)) | R19: =IF(OR(F19="",J19="",F19="NA",J19="NA"),"",ROUND(IF(F19>J19,F19-J19,0),-1)) | T19: =IF(S19="Yes","Report","No Action") | V19: Y
K20: =IF(OR(C20="",E20="",C20="NA",E20="NA"),"",ROUND(C20-E20,-1)) | L20: =IF(OR(D20="",F20="",D20="NA",F20="NA"),"",ROUND(D20-F20,-1)) | M20: =IF(OR(C20="",G20="",C20="NA",G20="NA"),"",ROUND(C20-G20,-1)) | N20: =IF(OR(D20="",H20="",D20="NA",H20="NA"),"",ROUND(D20-H20,-1)) | O20: =IF(OR(E20="",G20="",E20="NA",G20="NA"),"",ROUND(E20-G20,-1)) | P20: =IF(OR(F20="",H20="",F20="NA",H20="NA"),"",ROUND(F20-H20,-1)) | Q20: =IF(OR(E20="",I20="",E20="NA",I20="NA"),"",ROUND(IF(E20>I20,E20-I20,0),-1)) | R20: =IF(OR(F20="",J20="",F20="NA",J20="NA"),"",ROUND(IF(F20>J20,F20-J20,0),-1)) | T20: =IF(S20="Yes","Report","No Action") | V20: Y
K21: =IF(OR(C21="",E21="",C21="NA",E21="NA"),"",ROUND(C21-E21,-1)) | L21: =IF(OR(D21="",F21="",D21="NA",F21="NA"),"",ROUND(D21-F21,-1)) | M21: =IF(OR(C21="",G21="",C21="NA",G21="NA"),"",ROUND(C21-G21,-1)) | N21: =IF(OR(D21="",H21="",D21="NA",H21="NA"),"",ROUND(D21-H21,-1)) | O21: =IF(OR(E21="",G21="",E21="NA",G21="NA"),"",ROUND(E21-G21,-1)) | P21: =IF(OR(F21="",H21="",F21="NA",H21="NA"),"",ROUND(F21-H21,-1)) | Q21: =IF(OR(E21="",I21="",E21="NA",I21="NA"),"",ROUND(IF(E21>I21,E21-I21,0),-1)) | R21: =IF(OR(F21="",J21="",F21="NA",J21="NA"),"",ROUND(IF(F21>J21,F21-J21,0),-1)) | T21: =IF(S21="Yes","Report","No Action") | V21: Y
K22: =IF(OR(C22="",E22="",C22="NA",E22="NA"),"",ROUND(C22-E22,-1)) | L22: =IF(OR(D22="",F22="",D22="NA",F22="NA"),"",ROUND(D22-F22,-1)) | M22: =IF(OR(C22="",G22="",C22="NA",G22="NA"),"",ROUND(C22-G22,-1)) | N22: =IF(OR(D22="",H22="",D22="NA",H22="NA"),"",ROUND(D22-H22,-1)) | O22: =IF(OR(E22="",G22="",E22="NA",G22="NA"),"",ROUND(E22-G22,-1)) | P22: =IF(OR(F22="",H22="",F22="NA",H22="NA"),"",ROUND(F22-H22,-1)) | Q22: =IF(OR(E22="",I22="",E22="NA",I22="NA"),"",ROUND(IF(E22>I22,E22-I22,0),-1)) | R22: =IF(OR(F22="",J22="",F22="NA",J22="NA"),"",ROUND(IF(F22>J22,F22-J22,0),-1)) | T22: =IF(S22="Yes","Report","No Action") | V22: Y
K23: =IF(OR(C23="",E23="",C23="NA",E23="NA"),"",ROUND(C23-E23,-1)) | L23: =IF(OR(D23="",F23="",D23="NA",F23="NA"),"",ROUND(D23-F23,-1)) | M23: =IF(OR(C23="",G23="",C23="NA",G23="NA"),"",ROUND(C23-G23,-1)) | N23: =IF(OR(D23="",H23="",D23="NA",H23="NA"),"",ROUND(D23-H23,-1)) | O23: =IF(OR(E23="",G23="",E23="NA",G23="NA"),"",ROUND(E23-G23,-1)) | P23: =IF(OR(F23="",H23="",F23="NA",H23="NA"),"",ROUND(F23-H23,-1)) | Q23: =IF(OR(E23="",I23="",E23="NA",I23="NA"),"",ROUND(IF(E23>I23,E23-I23,0),-1)) | R23: =IF(OR(F23="",J23="",F23="NA",J23="NA"),"",ROUND(IF(F23>J23,F23-J23,0),-1)) | T23: =IF(S23="Yes","Report","No Action") | V23: Y
... K65: =IF(OR(C65="",E65="",C65="NA",E65="NA"),"",ROUND(C65-E65,-1)) | L65: =IF(OR(D65="",F65="",D65="NA",F65="NA"),"",ROUND(D65-F65,-1)) | M65: =IF(OR(C65="",G65="",C65="NA",G65="NA"),"",ROUND(C65-G65,-1)) | N65: =IF(OR(D65="",H65="",D65="NA",H65="NA"),"",ROUND(D65-H65,-1)) | O65: =IF(OR(E65="",G65="",E65="NA",G65="NA"),"",ROUND(E65-G65,-1)) | P65: =IF(OR(F65="",H65="",F65="NA",H65="NA"),"",ROUND(F65-H65,-1)) | Q65: =IF(OR(E65="",I65="",E65="NA",I65="NA"),"",ROUND(IF(E65>I65,E65-I65,0),-1)) | R65: =IF(OR(F65="",J65="",F65="NA",J65="NA"),"",ROUND(IF(F65>J65,F65-J65,0),-1)) | T65: =IF(S65="Yes","Report","No Action") | V65: Y
K66: =IF(OR(C66="",E66="",C66="NA",E66="NA"),"",ROUND(C66-E66,-1)) | L66: =IF(OR(D66="",F66="",D66="NA",F66="NA"),"",ROUND(D66-F66,-1)) | M66: =IF(OR(C66="",G66="",C66="NA",G66="NA"),"",ROUND(C66-G66,-1)) | N66: =IF(OR(D66="",H66="",D66="NA",H66="NA"),"",ROUND(D66-H66,-1)) | O66: =IF(OR(E66="",G66="",E66="NA",G66="NA"),"",ROUND(E66-G66,-1)) | P66: =IF(OR(F66="",H66="",F66="NA",H66="NA"),"",ROUND(F66-H66,-1)) | Q66: =IF(OR(E66="",I66="",E66="NA",I66="NA"),"",ROUND(IF(E66>I66,E66-I66,0),-1)) | R66: =IF(OR(F66="",J66="",F66="NA",J66="NA"),"",ROUND(IF(F66>J66,F66-J66,0),-1)) | T66: No Action | V66: Y
K67: =IF(OR(C67="",E67="",C67="NA",E67="NA"),"",ROUND(C67-E67,-1)) | L67: =IF(OR(D67="",F67="",D67="NA",F67="NA"),"",ROUND(D67-F67,-1)) | M67: =IF(OR(C67="",G67="",C67="NA",G67="NA"),"",ROUND(C67-G67,-1)) | N67: =IF(OR(D67="",H67="",D67="NA",H67="NA"),"",ROUND(D67-H67,-1)) | O67: =IF(OR(E67="",G67="",E67="NA",G67="NA"),"",ROUND(E67-G67,-1)) | P67: =IF(OR(F67="",H67="",F67="NA",H67="NA"),"",ROUND(F67-H67,-1)) | Q67: =IF(OR(E67="",I67="",E67="NA",I67="NA"),"",ROUND(IF(E67>I67,E67-I67,0),-1)) | R67: =IF(OR(F67="",J67="",F67="NA",J67="NA"),"",ROUND(IF(F67>J67,F67-J67,0),-1)) | T67: No Action | V67: Y
K68: =IF(OR(C68="",E68="",C68="NA",E68="NA"),"",ROUND(C68-E68,-1)) | L68: =IF(OR(D68="",F68="",D68="NA",F68="NA"),"",ROUND(D68-F68,-1)) | M68: =IF(OR(C68="",G68="",C68="NA",G68="NA"),"",ROUND(C68-G68,-1)) | N68: =IF(OR(D68="",H68="",D68="NA",H68="NA"),"",ROUND(D68-H68,-1)) | O68: =IF(OR(E68="",G68="",E68="NA",G68="NA"),"",ROUND(E68-G68,-1)) | P68: =IF(OR(F68="",H68="",F68="NA",H68="NA"),"",ROUND(F68-H68,-1)) | Q68: =IF(OR(E68="",I68="",E68="NA",I68="NA"),"",ROUND(IF(E68>I68,E68-I68,0),-1)) | R68: =IF(OR(F68="",J68="",F68="NA",J68="NA"),"",ROUND(IF(F68>J68,F68-J68,0),-1)) | T68: No Action | V68: Y
K69: =IF(OR(C69="",E69="",C69="NA",E69="NA"),"",ROUND(C69-E69,-1)) | L69: =IF(OR(D69="",F69="",D69="NA",F69="NA"),"",ROUND(D69-F69,-1)) | M69: =IF(OR(C69="",G69="",C69="NA",G69="NA"),"",ROUND(C69-G69,-1)) | N69: =IF(OR(D69="",H69="",D69="NA",H69="NA"),"",ROUND(D69-H69,-1)) | O69: =IF(OR(E69="",G69="",E69="NA",G69="NA"),"",ROUND(E69-G69,-1)) | P69: =IF(OR(F69="",H69="",F69="NA",H69="NA"),"",ROUND(F69-H69,-1)) | Q69: =IF(OR(E69="",I69="",E69="NA",I69="NA"),"",ROUND(IF(E69>I69,E69-I69,0),-1)) | R69: =IF(OR(F69="",J69="",F69="NA",J69="NA"),"",ROUND(IF(F69>J69,F69-J69,0),-1)) | T69: No Action | V69: Y
K70: =IF(OR(C70="",E70="",C70="NA",E70="NA"),"",ROUND(C70-E70,-1)) | L70: =IF(OR(D70="",F70="",D70="NA",F70="NA"),"",ROUND(D70-F70,-1)) | M70: =IF(OR(C70="",G70="",C70="NA",G70="NA"),"",ROUND(C70-G70,-1)) | N70: =IF(OR(D70="",H70="",D70="NA",H70="NA"),"",ROUND(D70-H70,-1)) | O70: =IF(OR(E70="",G70="",E70="NA",G70="NA"),"",ROUND(E70-G70,-1)) | P70: =IF(OR(F70="",H70="",F70="NA",H70="NA"),"",ROUND(F70-H70,-1)) | Q70: =IF(OR(E70="",I70="",E70="NA",I70="NA"),"",ROUND(IF(E70>I70,E70-I70,0),-1)) | R70: =IF(OR(F70="",J70="",F70="NA",J70="NA"),"",ROUND(IF(F70>J70,F70-J70,0),-1)) | T70: No Action | V70: Y
K71: =IF(OR(C71="",E71="",C71="NA",E71="NA"),"",ROUND(C71-E71,-1)) | L71: =IF(OR(D71="",F71="",D71="NA",F71="NA"),"",ROUND(D71-F71,-1)) | M71: =IF(OR(C71="",G71="",C71="NA",G71="NA"),"",ROUND(C71-G71,-1)) | N71: =IF(OR(D71="",H71="",D71="NA",H71="NA"),"",ROUND(D71-H71,-1)) | O71: =IF(OR(E71="",G71="",E71="NA",G71="NA"),"",ROUND(E71-G71,-1)) | P71: =IF(OR(F71="",H71="",F71="NA",H71="NA"),"",ROUND(F71-H71,-1)) | Q71: =IF(OR(E71="",I71="",E71="NA",I71="NA"),"",ROUND(IF(E71>I71,E71-I71,0),-1)) | R71: =IF(OR(F71="",J71="",F71="NA",J71="NA"),"",ROUND(IF(F71>J71,F71-J71,0),-1)) | T71: No Action | V71: Y
K72: =IF(OR(C72="",E72="",C72="NA",E72="NA"),"",ROUND(C72-E72,-1)) | L72: =IF(OR(D72="",F72="",D72="NA",F72="NA"),"",ROUND(D72-F72,-1)) | M72: =IF(OR(C72="",G72="",C72="NA",G72="NA"),"",ROUND(C72-G72,-1)) | N72: =IF(OR(D72="",H72="",D72="NA",H72="NA"),"",ROUND(D72-H72,-1)) | O72: =IF(OR(E72="",G72="",E72="NA",G72="NA"),"",ROUND(E72-G72,-1)) | P72: =IF(OR(F72="",H72="",F72="NA",H72="NA"),"",ROUND(F72-H72,-1)) | Q72: =IF(OR(E72="",I72="",E72="NA",I72="NA"),"",ROUND(IF(E72>I72,E72-I72,0),-1)) | R72: =IF(OR(F72="",J72="",F72="NA",J72="NA"),"",ROUND(IF(F72>J72,F72-J72,0),-1)) | T72: No Action | V72: Y
K73: =IF(OR(C73="",E73="",C73="NA",E73="NA"),"",ROUND(C73-E73,-1)) | L73: =IF(OR(D73="",F73="",D73="NA",F73="NA"),"",ROUND(D73-F73,-1)) | M73: =IF(OR(C73="",G73="",C73="NA",G73="NA"),"",ROUND(C73-G73,-1)) | N73: =IF(OR(D73="",H73="",D73="NA",H73="NA"),"",ROUND(D73-H73,-1)) | O73: =IF(OR(E73="",G73="",E73="NA",G73="NA"),"",ROUND(E73-G73,-1)) | P73: =IF(OR(F73="",H73="",F73="NA",H73="NA"),"",ROUND(F73-H73,-1)) | Q73: =IF(OR(E73="",I73="",E73="NA",I73="NA"),"",ROUND(IF(E73>I73,E73-I73,0),-1)) | R73: =IF(OR(F73="",J73="",F73="NA",J73="NA"),"",ROUND(IF(F73>J73,F73-J73,0),-1)) | T73: No Action | V73: Y
K74: =IF(OR(C74="",E74="",C74="NA",E74="NA"),"",ROUND(C74-E74,-1)) | L74: =IF(OR(D74="",F74="",D74="NA",F74="NA"),"",ROUND(D74-F74,-1)) | M74: =IF(OR(C74="",G74="",C74="NA",G74="NA"),"",ROUND(C74-G74,-1)) | N74: =IF(OR(D74="",H74="",D74="NA",H74="NA"),"",ROUND(D74-H74,-1)) | O74: =IF(OR(E74="",G74="",E74="NA",G74="NA"),"",ROUND(E74-G74,-1)) | P74: =IF(OR(F74="",H74="",F74="NA",H74="NA"),"",ROUND(F74-H74,-1)) | Q74: =IF(OR(E74="",I74="",E74="NA",I74="NA"),"",ROUND(IF(E74>I74,E74-I74,0),-1)) | R74: =IF(OR(F74="",J74="",F74="NA",J74="NA"),"",ROUND(IF(F74>J74,F74-J74,0),-1)) | T74: No Action | V74: Y
K75: =IF(OR(C75="",E75="",C75="NA",E75="NA"),"",ROUND(C75-E75,-1)) | L75: =IF(OR(D75="",F75="",D75="NA",F75="NA"),"",ROUND(D75-F75,-1)) | M75: =IF(OR(C75="",G75="",C75="NA",G75="NA"),"",ROUND(C75-G75,-1)) | N75: =IF(OR(D75="",H75="",D75="NA",H75="NA"),"",ROUND(D75-H75,-1)) | O75: =IF(OR(E75="",G75="",E75="NA",G75="NA"),"",ROUND(E75-G75,-1)) | P75: =IF(OR(F75="",H75="",F75="NA",H75="NA"),"",ROUND(F75-H75,-1)) | Q75: =IF(OR(E75="",I75="",E75="NA",I75="NA"),"",ROUND(IF(E75>I75,E75-I75,0),-1)) | R75: =IF(OR(F75="",J75="",F75="NA",J75="NA"),"",ROUND(IF(F75>J75,F75-J75,0),-1)) | T75: No Action | V75: Y
K76: =IF(OR(C76="",E76="",C76="NA",E76="NA"),"",ROUND(C76-E76,-1)) | L76: =IF(OR(D76="",F76="",D76="NA",F76="NA"),"",ROUND(D76-F76,-1)) | M76: =IF(OR(C76="",G76="",C76="NA",G76="NA"),"",ROUND(C76-G76,-1)) | N76: =IF(OR(D76="",H76="",D76="NA",H76="NA"),"",ROUND(D76-H76,-1)) | O76: =IF(OR(E76="",G76="",E76="NA",G76="NA"),"",ROUND(E76-G76,-1)) | P76: =IF(OR(F76="",H76="",F76="NA",H76="NA"),"",ROUND(F76-H76,-1)) | Q76: =IF(OR(E76="",I76="",E76="NA",I76="NA"),"",ROUND(IF(E76>I76,E76-I76,0),-1)) | R76: =IF(OR(F76="",J76="",F76="NA",J76="NA"),"",ROUND(IF(F76>J76,F76-J76,0),-1)) | T76: No Action | V76: Y
K77: =IF(OR(C77="",E77="",C77="NA",E77="NA"),"",ROUND(C77-E77,-1)) | L77: =IF(OR(D77="",F77="",D77="NA",F77="NA"),"",ROUND(D77-F77,-1)) | M77: =IF(OR(C77="",G77="",C77="NA",G77="NA"),"",ROUND(C77-G77,-1)) | N77: =IF(OR(D77="",H77="",D77="NA",H77="NA"),"",ROUND(D77-H77,-1)) | O77: =IF(OR(E77="",G77="",E77="NA",G77="NA"),"",ROUND(E77-G77,-1)) | P77: =IF(OR(F77="",H77="",F77="NA",H77="NA"),"",ROUND(F77-H77,-1)) | Q77: =IF(OR(E77="",I77="",E77="NA",I77="NA"),"",ROUND(IF(E77>I77,E77-I77,0),-1)) | R77: =IF(OR(F77="",J77="",F77="NA",J77="NA"),"",ROUND(IF(F77>J77,F77-J77,0),-1)) | T77: No Action | V77: Y
... K161: =IF(OR(C161="",E161="",C161="NA",E161="NA"),"",ROUND(C161-E161,-1)) | L161: =IF(OR(D161="",F161="",D161="NA",F161="NA"),"",ROUND(D161-F161,-1)) | M161: =IF(OR(C161="",G161="",C161="NA",G161="NA"),"",ROUND(C161-G161,-1)) | N161: =IF(OR(D161="",H161="",D161="NA",H161="NA"),"",ROUND(D161-H161,-1)) | O161: =IF(OR(E161="",G161="",E161="NA",G161="NA"),"",ROUND(E161-G161,-1)) | P161: =IF(OR(F161="",H161="",F161="NA",H161="NA"),"",ROUND(F161-H161,-1)) | Q161: =IF(OR(E161="",I161="",E161="NA",I161="NA"),"",ROUND(IF(E161>I161,E161-I161,0),-1)) | R161: =IF(OR(F161="",J161="",F161="NA",J161="NA"),"",ROUND(IF(F161>J161,F161-J161,0),-1)) | T161: No Action | V161: Y

Sheet Summary
A1: PAVAN JAIN S AND CO |CHARTERED ACCOUNTANTS
A3: AIS/TIS/26AS/BOOKS COMPARATIVE SUMMARY
A5: NAME OF THE CLIENT
A6: ASSESSMENT YEAR
A7: FINANCIAL YEAR
A8: PREPARED BY
A11: Nature of Transactions | B11: 26AS | D11: AIS | F11: TIS | H11: Books | J11: Difference
B12: Gross Value | C12: TDS/TCS | D12: Gross Value | E12: TDS/TCS | F12: Gross Value | G12: TDS/TCS | H12: Gross Value | I12: TDS/TCS | J12: 26AS/AIS | L12: 26AS/TIS | N12: AIS/TIS | P12: Books/TIS
A13: =Masters!C2 | B13: =SUMIFS(Reco!$C$12:$C$161,Reco!$A$12:$A$161,$A13,Reco!$V$12:$V$161,"Y") | C13: =SUMIFS(Reco!$D$12:$D$161,Reco!$A$12:$A$161,$A13,Reco!$V$12:$V$161,"Y") | D13: =SUMIFS(Reco!$E$12:$E$161,Reco!$A$12:$A$161,$A13,Reco!$V$12:$V$161,"Y") | E13: =SUMIFS(Reco!$F$12:$F$161,Reco!$A$12:$A$161,$A13,Reco!$V$12:$V$161,"Y") | F13: =SUMIFS(Reco!$G$12:$G$161,Reco!$A$12:$A$161,$A13,Reco!$V$12:$V$161,"Y") | G13: =SUMIFS(Reco!$H$12:$H$161,Reco!$A$12:$A$161,$A13,Reco!$V$12:$V$161,"Y") | H13: =SUMIFS(Reco!$I$12:$I$161,Reco!$A$12:$A$161,$A13,Reco!$V$12:$V$161,"Y") | I13: =SUMIFS(Reco!$J$12:$J$161,Reco!$A$12:$A$161,$A13,Reco!$V$12:$V$161,"Y") | J13: =IF(OR(B13="",D13=""),"",ROUND(B13-D13,-1)) | K13: =IF(OR(C13="",E13=""),"",ROUND(C13-E13,-1)) | L13: =IF(OR(B13="",F13=""),"",ROUND(B13-F13,-1)) | M13: =IF(OR(C13="",G13=""),"",ROUND(C13-G13,-1)) | N13: =IF(OR(D13="",F13=""),"",ROUND(D13-F13,-1)) | O13: =IF(OR(E13="",G13=""),"",ROUND(E13-G13,-1)) | P13: =IF(OR(F13="",H13=""),"",ROUND(F13-H13,-1)) | Q13: =IF(OR(I13="",G13=""),"",ROUND(G13-I13,-1))
A14: =Masters!C3 | B14: =SUMIFS(Reco!$C$12:$C$161,Reco!$A$12:$A$161,$A14,Reco!$V$12:$V$161,"Y") | C14: =SUMIFS(Reco!$D$12:$D$161,Reco!$A$12:$A$161,$A14,Reco!$V$12:$V$161,"Y") | D14: =SUMIFS(Reco!$E$12:$E$161,Reco!$A$12:$A$161,$A14,Reco!$V$12:$V$161,"Y") | E14: =SUMIFS(Reco!$F$12:$F$161,Reco!$A$12:$A$161,$A14,Reco!$V$12:$V$161,"Y") | F14: =SUMIFS(Reco!$G$12:$G$161,Reco!$A$12:$A$161,$A14,Reco!$V$12:$V$161,"Y") | G14: =SUMIFS(Reco!$H$12:$H$161,Reco!$A$12:$A$161,$A14,Reco!$V$12:$V$161,"Y") | H14: =SUMIFS(Reco!$I$12:$I$161,Reco!$A$12:$A$161,$A14,Reco!$V$12:$V$161,"Y") | I14: =SUMIFS(Reco!$J$12:$J$161,Reco!$A$12:$A$161,$A14,Reco!$V$12:$V$161,"Y") | J14: =IF(OR(B14="",D14=""),"",ROUND(B14-D14,-1)) | K14: =IF(OR(C14="",E14=""),"",ROUND(C14-E14,-1)) | L14: =IF(OR(B14="",F14=""),"",ROUND(B14-F14,-1)) | M14: =IF(OR(C14="",G14=""),"",ROUND(C14-G14,-1)) | N14: =IF(OR(D14="",F14=""),"",ROUND(D14-F14,-1)) | O14: =IF(OR(E14="",G14=""),"",ROUND(E14-G14,-1)) | P14: =IF(OR(F14="",H14=""),"",ROUND(F14-H14,-1)) | Q14: =IF(OR(I14="",G14=""),"",ROUND(G14-I14,-1))
A15: =Masters!C4 | B15: =SUMIFS(Reco!$C$12:$C$161,Reco!$A$12:$A$161,$A15,Reco!$V$12:$V$161,"Y") | C15: =SUMIFS(Reco!$D$12:$D$161,Reco!$A$12:$A$161,$A15,Reco!$V$12:$V$161,"Y") | D15: =SUMIFS(Reco!$E$12:$E$161,Reco!$A$12:$A$161,$A15,Reco!$V$12:$V$161,"Y") | E15: =SUMIFS(Reco!$F$12:$F$161,Reco!$A$12:$A$161,$A15,Reco!$V$12:$V$161,"Y") | F15: =SUMIFS(Reco!$G$12:$G$161,Reco!$A$12:$A$161,$A15,Reco!$V$12:$V$161,"Y") | G15: =SUMIFS(Reco!$H$12:$H$161,Reco!$A$12:$A$161,$A15,Reco!$V$12:$V$161,"Y") | H15: =SUMIFS(Reco!$I$12:$I$161,Reco!$A$12:$A$161,$A15,Reco!$V$12:$V$161,"Y") | I15: =SUMIFS(Reco!$J$12:$J$161,Reco!$A$12:$A$161,$A15,Reco!$V$12:$V$161,"Y") | J15: =IF(OR(B15="",D15=""),"",ROUND(B15-D15,-1)) | K15: =IF(OR(C15="",E15=""),"",ROUND(C15-E15,-1)) | L15: =IF(OR(B15="",F15=""),"",ROUND(B15-F15,-1)) | M15: =IF(OR(C15="",G15=""),"",ROUND(C15-G15,-1)) | N15: =IF(OR(D15="",F15=""),"",ROUND(D15-F15,-1)) | O15: =IF(OR(E15="",G15=""),"",ROUND(E15-G15,-1)) | P15: =IF(OR(F15="",H15=""),"",ROUND(F15-H15,-1)) | Q15: =IF(OR(I15="",G15=""),"",ROUND(G15-I15,-1))
A16: =Masters!C5 | B16: =SUMIFS(Reco!$C$12:$C$161,Reco!$A$12:$A$161,$A16,Reco!$V$12:$V$161,"Y") | C16: =SUMIFS(Reco!$D$12:$D$161,Reco!$A$12:$A$161,$A16,Reco!$V$12:$V$161,"Y") | D16: =SUMIFS(Reco!$E$12:$E$161,Reco!$A$12:$A$161,$A16,Reco!$V$12:$V$161,"Y") | E16: =SUMIFS(Reco!$F$12:$F$161,Reco!$A$12:$A$161,$A16,Reco!$V$12:$V$161,"Y") | F16: =SUMIFS(Reco!$G$12:$G$161,Reco!$A$12:$A$161,$A16,Reco!$V$12:$V$161,"Y") | G16: =SUMIFS(Reco!$H$12:$H$161,Reco!$A$12:$A$161,$A16,Reco!$V$12:$V$161,"Y") | H16: =SUMIFS(Reco!$I$12:$I$161,Reco!$A$12:$A$161,$A16,Reco!$V$12:$V$161,"Y") | I16: =SUMIFS(Reco!$J$12:$J$161,Reco!$A$12:$A$161,$A16,Reco!$V$12:$V$161,"Y") | J16: =IF(OR(B16="",D16=""),"",ROUND(B16-D16,-1)) | K16: =IF(OR(C16="",E16=""),"",ROUND(C16-E16,-1)) | L16: =IF(OR(B16="",F16=""),"",ROUND(B16-F16,-1)) | M16: =IF(OR(C16="",G16=""),"",ROUND(C16-G16,-1)) | N16: =IF(OR(D16="",F16=""),"",ROUND(D16-F16,-1)) | O16: =IF(OR(E16="",G16=""),"",ROUND(E16-G16,-1)) | P16: =IF(OR(F16="",H16=""),"",ROUND(F16-H16,-1)) | Q16: =IF(OR(I16="",G16=""),"",ROUND(G16-I16,-1))
A17: =Masters!C6 | B17: =SUMIFS(Reco!$C$12:$C$161,Reco!$A$12:$A$161,$A17,Reco!$V$12:$V$161,"Y") | C17: =SUMIFS(Reco!$D$12:$D$161,Reco!$A$12:$A$161,$A17,Reco!$V$12:$V$161,"Y") | D17: =SUMIFS(Reco!$E$12:$E$161,Reco!$A$12:$A$161,$A17,Reco!$V$12:$V$161,"Y") | E17: =SUMIFS(Reco!$F$12:$F$161,Reco!$A$12:$A$161,$A17,Reco!$V$12:$V$161,"Y") | F17: =SUMIFS(Reco!$G$12:$G$161,Reco!$A$12:$A$161,$A17,Reco!$V$12:$V$161,"Y") | G17: =SUMIFS(Reco!$H$12:$H$161,Reco!$A$12:$A$161,$A17,Reco!$V$12:$V$161,"Y") | H17: =SUMIFS(Reco!$I$12:$I$161,Reco!$A$12:$A$161,$A17,Reco!$V$12:$V$161,"Y") | I17: =SUMIFS(Reco!$J$12:$J$161,Reco!$A$12:$A$161,$A17,Reco!$V$12:$V$161,"Y") | J17: =IF(OR(B17="",D17=""),"",ROUND(B17-D17,-1)) | K17: =IF(OR(C17="",E17=""),"",ROUND(C17-E17,-1)) | L17: =IF(OR(B17="",F17=""),"",ROUND(B17-F17,-1)) | M17: =IF(OR(C17="",G17=""),"",ROUND(C17-G17,-1)) | N17: =IF(OR(D17="",F17=""),"",ROUND(D17-F17,-1)) | O17: =IF(OR(E17="",G17=""),"",ROUND(E17-G17,-1)) | P17: =IF(OR(F17="",H17=""),"",ROUND(F17-H17,-1)) | Q17: =IF(OR(I17="",G17=""),"",ROUND(G17-I17,-1))
A18: =Masters!C7 | B18: =SUMIFS(Reco!$C$12:$C$161,Reco!$A$12:$A$161,$A18,Reco!$V$12:$V$161,"Y") | C18: =SUMIFS(Reco!$D$12:$D$161,Reco!$A$12:$A$161,$A18,Reco!$V$12:$V$161,"Y") | D18: =SUMIFS(Reco!$E$12:$E$161,Reco!$A$12:$A$161,$A18,Reco!$V$12:$V$161,"Y") | E18: =SUMIFS(Reco!$F$12:$F$161,Reco!$A$12:$A$161,$A18,Reco!$V$12:$V$161,"Y") | F18: =SUMIFS(Reco!$G$12:$G$161,Reco!$A$12:$A$161,$A18,Reco!$V$12:$V$161,"Y") | G18: =SUMIFS(Reco!$H$12:$H$161,Reco!$A$12:$A$161,$A18,Reco!$V$12:$V$161,"Y") | H18: =SUMIFS(Reco!$I$12:$I$161,Reco!$A$12:$A$161,$A18,Reco!$V$12:$V$161,"Y") | I18: =SUMIFS(Reco!$J$12:$J$161,Reco!$A$12:$A$161,$A18,Reco!$V$12:$V$161,"Y") | J18: =IF(OR(B18="",D18=""),"",ROUND(B18-D18,-1)) | K18: =IF(OR(C18="",E18=""),"",ROUND(C18-E18,-1)) | L18: =IF(OR(B18="",F18=""),"",ROUND(B18-F18,-1)) | M18: =IF(OR(C18="",G18=""),"",ROUND(C18-G18,-1)) | N18: =IF(OR(D18="",F18=""),"",ROUND(D18-F18,-1)) | O18: =IF(OR(E18="",G18=""),"",ROUND(E18-G18,-1)) | P18: =IF(OR(F18="",H18=""),"",ROUND(F18-H18,-1)) | Q18: =IF(OR(I18="",G18=""),"",ROUND(G18-I18,-1))
A19: =Masters!C8 | B19: =SUMIFS(Reco!$C$12:$C$161,Reco!$A$12:$A$161,$A19,Reco!$V$12:$V$161,"Y") | C19: =SUMIFS(Reco!$D$12:$D$161,Reco!$A$12:$A$161,$A19,Reco!$V$12:$V$161,"Y") | D19: =SUMIFS(Reco!$E$12:$E$161,Reco!$A$12:$A$161,$A19,Reco!$V$12:$V$161,"Y") | E19: =SUMIFS(Reco!$F$12:$F$161,Reco!$A$12:$A$161,$A19,Reco!$V$12:$V$161,"Y") | F19: =SUMIFS(Reco!$G$12:$G$161,Reco!$A$12:$A$161,$A19,Reco!$V$12:$V$161,"Y") | G19: =SUMIFS(Reco!$H$12:$H$161,Reco!$A$12:$A$161,$A19,Reco!$V$12:$V$161,"Y") | H19: =SUMIFS(Reco!$I$12:$I$161,Reco!$A$12:$A$161,$A19,Reco!$V$12:$V$161,"Y") | I19: =SUMIFS(Reco!$J$12:$J$161,Reco!$A$12:$A$161,$A19,Reco!$V$12:$V$161,"Y") | J19: =IF(OR(B19="",D19=""),"",ROUND(B19-D19,-1)) | K19: =IF(OR(C19="",E19=""),"",ROUND(C19-E19,-1)) | L19: =IF(OR(B19="",F19=""),"",ROUND(B19-F19,-1)) | M19: =IF(OR(C19="",G19=""),"",ROUND(C19-G19,-1)) | N19: =IF(OR(D19="",F19=""),"",ROUND(D19-F19,-1)) | O19: =IF(OR(E19="",G19=""),"",ROUND(E19-G19,-1)) | P19: =IF(OR(F19="",H19=""),"",ROUND(F19-H19,-1)) | Q19: =IF(OR(I19="",G19=""),"",ROUND(G19-I19,-1))
A20: =Masters!C9 | B20: =SUMIFS(Reco!$C$12:$C$161,Reco!$A$12:$A$161,$A20,Reco!$V$12:$V$161,"Y") | C20: =SUMIFS(Reco!$D$12:$D$161,Reco!$A$12:$A$161,$A20,Reco!$V$12:$V$161,"Y") | D20: =SUMIFS(Reco!$E$12:$E$161,Reco!$A$12:$A$161,$A20,Reco!$V$12:$V$161,"Y") | E20: =SUMIFS(Reco!$F$12:$F$161,Reco!$A$12:$A$161,$A20,Reco!$V$12:$V$161,"Y") | F20: =SUMIFS(Reco!$G$12:$G$161,Reco!$A$12:$A$161,$A20,Reco!$V$12:$V$161,"Y") | G20: =SUMIFS(Reco!$H$12:$H$161,Reco!$A$12:$A$161,$A20,Reco!$V$12:$V$161,"Y") | H20: =SUMIFS(Reco!$I$12:$I$161,Reco!$A$12:$A$161,$A20,Reco!$V$12:$V$161,"Y") | I20: =SUMIFS(Reco!$J$12:$J$161,Reco!$A$12:$A$161,$A20,Reco!$V$12:$V$161,"Y") | J20: =IF(OR(B20="",D20=""),"",ROUND(B20-D20,-1)) | K20: =IF(OR(C20="",E20=""),"",ROUND(C20-E20,-1)) | L20: =IF(OR(B20="",F20=""),"",ROUND(B20-F20,-1)) | M20: =IF(OR(C20="",G20=""),"",ROUND(C20-G20,-1)) | N20: =IF(OR(D20="",F20=""),"",ROUND(D20-F20,-1)) | O20: =IF(OR(E20="",G20=""),"",ROUND(E20-G20,-1)) | P20: =IF(OR(F20="",H20=""),"",ROUND(F20-H20,-1)) | Q20: =IF(OR(I20="",G20=""),"",ROUND(G20-I20,-1))
A21: =Masters!C10 | B21: =SUMIFS(Reco!$C$12:$C$161,Reco!$A$12:$A$161,$A21,Reco!$V$12:$V$161,"Y") | C21: =SUMIFS(Reco!$D$12:$D$161,Reco!$A$12:$A$161,$A21,Reco!$V$12:$V$161,"Y") | D21: =SUMIFS(Reco!$E$12:$E$161,Reco!$A$12:$A$161,$A21,Reco!$V$12:$V$161,"Y") | E21: =SUMIFS(Reco!$F$12:$F$161,Reco!$A$12:$A$161,$A21,Reco!$V$12:$V$161,"Y") | F21: =SUMIFS(Reco!$G$12:$G$161,Reco!$A$12:$A$161,$A21,Reco!$V$12:$V$161,"Y") | G21: =SUMIFS(Reco!$H$12:$H$161,Reco!$A$12:$A$161,$A21,Reco!$V$12:$V$161,"Y") | H21: =SUMIFS(Reco!$I$12:$I$161,Reco!$A$12:$A$161,$A21,Reco!$V$12:$V$161,"Y") | I21: =SUMIFS(Reco!$J$12:$J$161,Reco!$A$12:$A$161,$A21,Reco!$V$12:$V$161,"Y") | J21: =IF(OR(B21="",D21=""),"",ROUND(B21-D21,-1)) | K21: =IF(OR(C21="",E21=""),"",ROUND(C21-E21,-1)) | L21: =IF(OR(B21="",F21=""),"",ROUND(B21-F21,-1)) | M21: =IF(OR(C21="",G21=""),"",ROUND(C21-G21,-1)) | N21: =IF(OR(D21="",F21=""),"",ROUND(D21-F21,-1)) | O21: =IF(OR(E21="",G21=""),"",ROUND(E21-G21,-1)) | P21: =IF(OR(F21="",H21=""),"",ROUND(F21-H21,-1)) | Q21: =IF(OR(I21="",G21=""),"",ROUND(G21-I21,-1))
A22: =Masters!C11 | B22: =SUMIFS(Reco!$C$12:$C$161,Reco!$A$12:$A$161,$A22,Reco!$V$12:$V$161,"Y") | C22: =SUMIFS(Reco!$D$12:$D$161,Reco!$A$12:$A$161,$A22,Reco!$V$12:$V$161,"Y") | D22: =SUMIFS(Reco!$E$12:$E$161,Reco!$A$12:$A$161,$A22,Reco!$V$12:$V$161,"Y") | E22: =SUMIFS(Reco!$F$12:$F$161,Reco!$A$12:$A$161,$A22,Reco!$V$12:$V$161,"Y") | F22: =SUMIFS(Reco!$G$12:$G$161,Reco!$A$12:$A$161,$A22,Reco!$V$12:$V$161,"Y") | G22: =SUMIFS(Reco!$H$12:$H$161,Reco!$A$12:$A$161,$A22,Reco!$V$12:$V$161,"Y") | H22: =SUMIFS(Reco!$I$12:$I$161,Reco!$A$12:$A$161,$A22,Reco!$V$12:$V$161,"Y") | I22: =SUMIFS(Reco!$J$12:$J$161,Reco!$A$12:$A$161,$A22,Reco!$V$12:$V$161,"Y") | J22: =IF(OR(B22="",D22=""),"",ROUND(B22-D22,-1)) | K22: =IF(OR(C22="",E22=""),"",ROUND(C22-E22,-1)) | L22: =IF(OR(B22="",F22=""),"",ROUND(B22-F22,-1)) | M22: =IF(OR(C22="",G22=""),"",ROUND(C22-G22,-1)) | N22: =IF(OR(D22="",F22=""),"",ROUND(D22-F22,-1)) | O22: =IF(OR(E22="",G22=""),"",ROUND(E22-G22,-1)) | P22: =IF(OR(F22="",H22=""),"",ROUND(F22-H22,-1)) | Q22: =IF(OR(I22="",G22=""),"",ROUND(G22-I22,-1))
A23: =Masters!C12 | B23: =SUMIFS(Reco!$C$12:$C$161,Reco!$A$12:$A$161,$A23,Reco!$V$12:$V$161,"Y") | C23: =SUMIFS(Reco!$D$12:$D$161,Reco!$A$12:$A$161,$A23,Reco!$V$12:$V$161,"Y") | D23: =SUMIFS(Reco!$E$12:$E$161,Reco!$A$12:$A$161,$A23,Reco!$V$12:$V$161,"Y") | E23: =SUMIFS(Reco!$F$12:$F$161,Reco!$A$12:$A$161,$A23,Reco!$V$12:$V$161,"Y") | F23: =SUMIFS(Reco!$G$12:$G$161,Reco!$A$12:$A$161,$A23,Reco!$V$12:$V$161,"Y") | G23: =SUMIFS(Reco!$H$12:$H$161,Reco!$A$12:$A$161,$A23,Reco!$V$12:$V$161,"Y") | H23: =SUMIFS(Reco!$I$12:$I$161,Reco!$A$12:$A$161,$A23,Reco!$V$12:$V$161,"Y") | I23: =SUMIFS(Reco!$J$12:$J$161,Reco!$A$12:$A$161,$A23,Reco!$V$12:$V$161,"Y") | J23: =IF(OR(B23="",D23=""),"",ROUND(B23-D23,-1)) | K23: =IF(OR(C23="",E23=""),"",ROUND(C23-E23,-1)) | L23: =IF(OR(B23="",F23=""),"",ROUND(B23-F23,-1)) | M23: =IF(OR(C23="",G23=""),"",ROUND(C23-G23,-1)) | N23: =IF(OR(D23="",F23=""),"",ROUND(D23-F23,-1)) | O23: =IF(OR(E23="",G23=""),"",ROUND(E23-G23,-1)) | P23: =IF(OR(F23="",H23=""),"",ROUND(F23-H23,-1)) | Q23: =IF(OR(I23="",G23=""),"",ROUND(G23-I23,-1))
A24: =Masters!C13 | B24: =SUMIFS(Reco!$C$12:$C$161,Reco!$A$12:$A$161,$A24,Reco!$V$12:$V$161,"Y") | C24: =SUMIFS(Reco!$D$12:$D$161,Reco!$A$12:$A$161,$A24,Reco!$V$12:$V$161,"Y") | D24: =SUMIFS(Reco!$E$12:$E$161,Reco!$A$12:$A$161,$A24,Reco!$V$12:$V$161,"Y") | E24: =SUMIFS(Reco!$F$12:$F$161,Reco!$A$12:$A$161,$A24,Reco!$V$12:$V$161,"Y") | F24: =SUMIFS(Reco!$G$12:$G$161,Reco!$A$12:$A$161,$A24,Reco!$V$12:$V$161,"Y") | G24: =SUMIFS(Reco!$H$12:$H$161,Reco!$A$12:$A$161,$A24,Reco!$V$12:$V$161,"Y") | H24: =SUMIFS(Reco!$I$12:$I$161,Reco!$A$12:$A$161,$A24,Reco!$V$12:$V$161,"Y") | I24: =SUMIFS(Reco!$J$12:$J$161,Reco!$A$12:$A$161,$A24,Reco!$V$12:$V$161,"Y") | J24: =IF(OR(B24="",D24=""),"",ROUND(B24-D24,-1)) | K24: =IF(OR(C24="",E24=""),"",ROUND(C24-E24,-1)) | L24: =IF(OR(B24="",F24=""),"",ROUND(B24-F24,-1)) | M24: =IF(OR(C24="",G24=""),"",ROUND(C24-G24,-1)) | N24: =IF(OR(D24="",F24=""),"",ROUND(D24-F24,-1)) | O24: =IF(OR(E24="",G24=""),"",ROUND(E24-G24,-1)) | P24: =IF(OR(F24="",H24=""),"",ROUND(F24-H24,-1)) | Q24: =IF(OR(I24="",G24=""),"",ROUND(G24-I24,-1))
... A35: =Masters!C24 | B35: =SUMIFS(Reco!$C$12:$C$161,Reco!$A$12:$A$161,$A35,Reco!$V$12:$V$161,"Y") | C35: =SUMIFS(Reco!$D$12:$D$161,Reco!$A$12:$A$161,$A35,Reco!$V$12:$V$161,"Y") | D35: =SUMIFS(Reco!$E$12:$E$161,Reco!$A$12:$A$161,$A35,Reco!$V$12:$V$161,"Y") | E35: =SUMIFS(Reco!$F$12:$F$161,Reco!$A$12:$A$161,$A35,Reco!$V$12:$V$161,"Y") | F35: =SUMIFS(Reco!$G$12:$G$161,Reco!$A$12:$A$161,$A35,Reco!$V$12:$V$161,"Y") | G35: =SUMIFS(Reco!$H$12:$H$161,Reco!$A$12:$A$161,$A35,Reco!$V$12:$V$161,"Y") | H35: =SUMIFS(Reco!$I$12:$I$161,Reco!$A$12:$A$161,$A35,Reco!$V$12:$V$161,"Y") | I35: =SUMIFS(Reco!$J$12:$J$161,Reco!$A$12:$A$161,$A35,Reco!$V$12:$V$161,"Y") | J35: =IF(OR(B35="",D35=""),"",ROUND(B35-D35,-1)) | K35: =IF(OR(C35="",E35=""),"",ROUND(C35-E35,-1)) | L35: =IF(OR(B35="",F35=""),"",ROUND(B35-F35,-1)) | M35: =IF(OR(C35="",G35=""),"",ROUND(C35-G35,-1)) | N35: =IF(OR(D35="",F35=""),"",ROUND(D35-F35,-1)) | O35: =IF(OR(E35="",G35=""),"",ROUND(E35-G35,-1)) | P35: =IF(OR(F35="",H35=""),"",ROUND(F35-H35,-1)) | Q35: =IF(OR(I35="",G35=""),"",ROUND(G35-I35,-1))
A36: =Masters!C25 | B36: =SUMIFS(Reco!$C$12:$C$161,Reco!$A$12:$A$161,$A36,Reco!$V$12:$V$161,"Y") | C36: =SUMIFS(Reco!$D$12:$D$161,Reco!$A$12:$A$161,$A36,Reco!$V$12:$V$161,"Y") | D36: =SUMIFS(Reco!$E$12:$E$161,Reco!$A$12:$A$161,$A36,Reco!$V$12:$V$161,"Y") | E36: =SUMIFS(Reco!$F$12:$F$161,Reco!$A$12:$A$161,$A36,Reco!$V$12:$V$161,"Y") | F36: =SUMIFS(Reco!$G$12:$G$161,Reco!$A$12:$A$161,$A36,Reco!$V$12:$V$161,"Y") | G36: =SUMIFS(Reco!$H$12:$H$161,Reco!$A$12:$A$161,$A36,Reco!$V$12:$V$161,"Y") | H36: =SUMIFS(Reco!$I$12:$I$161,Reco!$A$12:$A$161,$A36,Reco!$V$12:$V$161,"Y") | I36: =SUMIFS(Reco!$J$12:$J$161,Reco!$A$12:$A$161,$A36,Reco!$V$12:$V$161,"Y") | J36: =IF(OR(B36="",D36=""),"",ROUND(B36-D36,-1)) | K36: =IF(OR(C36="",E36=""),"",ROUND(C36-E36,-1)) | L36: =IF(OR(B36="",F36=""),"",ROUND(B36-F36,-1)) | M36: =IF(OR(C36="",G36=""),"",ROUND(C36-G36,-1)) | N36: =IF(OR(D36="",F36=""),"",ROUND(D36-F36,-1)) | O36: =IF(OR(E36="",G36=""),"",ROUND(E36-G36,-1)) | P36: =IF(OR(F36="",H36=""),"",ROUND(F36-H36,-1)) | Q36: =SUMIF(Reco!$A$12:$A$161,Summary!P36,Reco!$C$12:$C$161)
A37: Dividend Receipts | B37: =SUMIFS(Reco!$C$12:$C$161,Reco!$A$12:$A$161,$A37,Reco!$V$12:$V$161,"Y") | C37: =SUMIFS(Reco!$D$12:$D$161,Reco!$A$12:$A$161,$A37,Reco!$V$12:$V$161,"Y") | D37: =SUMIFS(Reco!$E$12:$E$161,Reco!$A$12:$A$161,$A37,Reco!$V$12:$V$161,"Y") | E37: =SUMIFS(Reco!$F$12:$F$161,Reco!$A$12:$A$161,$A37,Reco!$V$12:$V$161,"Y") | F37: =SUMIFS(Reco!$G$12:$G$161,Reco!$A$12:$A$161,$A37,Reco!$V$12:$V$161,"Y") | G37: =SUMIFS(Reco!$H$12:$H$161,Reco!$A$12:$A$161,$A37,Reco!$V$12:$V$161,"Y") | H37: =SUMIFS(Reco!$I$12:$I$161,Reco!$A$12:$A$161,$A37,Reco!$V$12:$V$161,"Y") | I37: =SUMIFS(Reco!$J$12:$J$161,Reco!$A$12:$A$161,$A37,Reco!$V$12:$V$161,"Y") | J37: =IF(OR(B37="",D37=""),"",ROUND(B37-D37,-1)) | K37: =IF(OR(C37="",E37=""),"",ROUND(C37-E37,-1)) | L37: =IF(OR(B37="",F37=""),"",ROUND(B37-F37,-1)) | M37: =IF(OR(C37="",G37=""),"",ROUND(C37-G37,-1)) | N37: =IF(OR(D37="",F37=""),"",ROUND(D37-F37,-1)) | O37: =IF(OR(E37="",G37=""),"",ROUND(E37-G37,-1)) | P37: =IF(OR(F37="",H37=""),"",ROUND(F37-H37,-1)) | Q37: =SUM(Q13:Q36)
A38: Other TDS/TCS | B38: =SUMIFS(Reco!$C$12:$C$161,Reco!$A$12:$A$161,$A38,Reco!$V$12:$V$161,"Y") | C38: =SUMIFS(Reco!$D$12:$D$161,Reco!$A$12:$A$161,$A38,Reco!$V$12:$V$161,"Y") | D38: =SUMIFS(Reco!$E$12:$E$161,Reco!$A$12:$A$161,$A38,Reco!$V$12:$V$161,"Y") | E38: =SUMIFS(Reco!$F$12:$F$161,Reco!$A$12:$A$161,$A38,Reco!$V$12:$V$161,"Y") | F38: =SUMIFS(Reco!$G$12:$G$161,Reco!$A$12:$A$161,$A38,Reco!$V$12:$V$161,"Y") | G38: =SUMIFS(Reco!$H$12:$H$161,Reco!$A$12:$A$161,$A38,Reco!$V$12:$V$161,"Y") | H38: =SUMIFS(Reco!$I$12:$I$161,Reco!$A$12:$A$161,$A38,Reco!$V$12:$V$161,"Y") | I38: =SUMIFS(Reco!$J$12:$J$161,Reco!$A$12:$A$161,$A38,Reco!$V$12:$V$161,"Y") | J38: =IF(OR(B38="",D38=""),"",ROUND(B38-D38,-1)) | K38: =IF(OR(C38="",E38=""),"",ROUND(C38-E38,-1)) | L38: =IF(OR(B38="",F38=""),"",ROUND(B38-F38,-1)) | M38: =IF(OR(C38="",G38=""),"",ROUND(C38-G38,-1)) | N38: =IF(OR(D38="",F38=""),"",ROUND(D38-F38,-1)) | O38: =IF(OR(E38="",G38=""),"",ROUND(E38-G38,-1)) | P38: =IF(OR(F38="",H38=""),"",ROUND(F38-H38,-1))
A39: TOTAL | B39: =SUM(B13:B38) | C39: =SUM(C13:C38) | D39: =SUM(D13:D38) | E39: =SUM(E13:E38) | F39: =SUM(F13:F38) | G39: =SUM(G13:G38) | H39: =SUM(H13:H38) | I39: =SUM(I13:I38) | ... P39: =SUM(P13:P38)

Sheet Masters
A2: 2021-22 | C2: 92B - Salaries Receipts | E2: Monish Guptha | G2: Yes
A3: 2022-23 | C3: 94C - Contract Receipts | E3: Hitanshi | G3: No
A4: 2023-24 | C4: 94JA - Technical Receipts | E4: Hari | G4: NA
A5: 2024-25 | C5: 94JB - Professional Receipts | E5: Harshita | G5: Can't Say
A6: 2025-26 | C6: 94IA - Rent Receipts (P & M) | E6: PJS
A7: 2026-27 | C7: 94IB - Rent Receipts (L & B) | E7: Others
C8: 94A - Interest Receipts | E8: Divya
C9: 94Q - Purchases
C10: 94H - Commission Receipts
C11: 94L - Property Transactions
C12: Purchase of Securities
C13: Sale of Securities
C14: GST Sales
C15: GST Purchases
C16: Advance Tax
C17: Cash Deposits
C18: Cash Withdrawals
C19: SAT
C20: 206CJ - TCS Purchases
... C27: Other TDS/TCS
